.gitignore
AUTHORS.rst
CONTRIBUTING.rst
HISTORY.rst
LICENSE
MANIFEST.in
Makefile
README.rst
pyproject.toml
.github/ISSUE_TEMPLATE.md
.github/workflows/publish.yml
docs/Makefile
docs/authors.rst
docs/conf.py
docs/contributing.rst
docs/history.rst
docs/index.rst
docs/installation.rst
docs/make.bat
docs/modules.rst
docs/readme.rst
docs/usage.rst
l2awinddirection/M64RN4.py
l2awinddirection/__init__.py
l2awinddirection/cli.py
l2awinddirection/config.yaml
l2awinddirection/generate_L2A_winddir_pdf_product.py
l2awinddirection/generate_L2A_winddir_regression_product.py
l2awinddirection/mainl2awinddirection.py
l2awinddirection/utils.py
l2awinddirection.egg-info/PKG-INFO
l2awinddirection.egg-info/SOURCES.txt
l2awinddirection.egg-info/dependency_links.txt
l2awinddirection.egg-info/entry_points.txt
l2awinddirection.egg-info/requires.txt
l2awinddirection.egg-info/top_level.txt
l2awinddirection/models/09h07_epoch_02__loss6.06.hdf5
tests/__init__.py
tests/test_l2awinddirection.py
tests/test_output_name.py